README.md
setup.py
./config/__init__.py
./config/logger.py
./executors/__init__.py
./executors/base.py
./executors/cli.py
./executors/docker_executor.py
./executors/gevent_executor.py
./executors/local_executor.py
./executors/main.py
./executors/multiprocessing_executor.py
./jat_queue.egg-info/PKG-INFO
./jat_queue.egg-info/SOURCES.txt
./jat_queue.egg-info/dependency_links.txt
./jat_queue.egg-info/entry_points.txt
./jat_queue.egg-info/requires.txt
./jat_queue.egg-info/top_level.txt
./tasks/__init__.py
./tasks/main.py
./tasks/scheduler.py
./tasks/tasks.py
./tasks/worker.py
./tests/__init__.py